picopy/__init__.py
picopy/picopy.py
picopy-1.0.12.dist-info/METADATA
picopy-1.0.12.dist-info/WHEEL
picopy-1.0.12.dist-info/entry_points.txt
picopy-1.0.12.dist-info/top_level.txt
picopy-1.0.12.dist-info/RECORD
