Metadata-Version: 2.1
Name: picopy
Version: 1.0.12
Summary: convert an image to a watercolor image 🎨
Home-page: https://github.com/Kiana-Jahanshid/picopy
Author: kiki js
Author-email: k.jhnshid@gmail.com
Requires-Dist: opencv-python
Requires-Dist: numpy
Requires-Dist: requests
